pylcurves/__init__.py
pylcurves/introduction.py
pylcurves/learning_curves.py
pylcurves-0.0.2.1.dist-info/DESCRIPTION.rst
pylcurves-0.0.2.1.dist-info/METADATA
pylcurves-0.0.2.1.dist-info/RECORD
pylcurves-0.0.2.1.dist-info/WHEEL
pylcurves-0.0.2.1.dist-info/entry_points.txt
pylcurves-0.0.2.1.dist-info/metadata.json
pylcurves-0.0.2.1.dist-info/top_level.txt
