Metadata-Version: 2.0
Name: pylcurves
Version: 0.0.2.1
Summary: My own package
Home-page: UNKNOWN
Author: ClementTr
Author-email: clement.tailleur@gmail.com
License: WTFPL
Platform: UNKNOWN
Classifier: Programming Language :: Python
Classifier: Development Status :: 1 - Planning
Classifier: License :: OSI Approved
Classifier: Natural Language :: French
Classifier: Operating System :: OS Independent
Classifier: Programming Language :: Python :: 3.6
Classifier: Topic :: Sociology
Requires-Dist: matplotlib (==1.5.3)
Requires-Dist: numpy (==1.12.1)
Requires-Dist: pandas (==0.20.2)
